opl/__init__.py
opl/cmds.py
opl/hdl.py
opl/obj.py
opl/run.py
opl/thr.py
opl/utl.py
oplib-226.data/scripts/opl
oplib-226.dist-info/METADATA
oplib-226.dist-info/WHEEL
oplib-226.dist-info/top_level.txt
oplib-226.dist-info/zip-safe
oplib-226.dist-info/RECORD
