Metadata-Version: 2.1
Name: oplib
Version: 226
Summary: object programming library
Home-page: https://github.com/bthate/oplib
Author: Bart Thate
Author-email: bthate67@gmail.com
License: Public Domain
Platform: UNKNOWN
Classifier: Development Status :: 4 - Beta
Classifier: License :: Public Domain
Classifier: Operating System :: Unix
Classifier: Programming Language :: Python
Classifier: Topic :: Utilities
